{
  "character/geme/starrail/ChamJadeHSRIllustriousXL.safetensors": {
    "triggerWords": ""
  },
  "character/geme/starrail/Char-HonkaiSR-Aglaea-V1-IL.safetensors": {
    "triggerWords": ""
  },
  "434/XXX_GangBang_IL_V1.safetensors": {
    "civitaiUrl": "https://civitai.com/models/654360",
    "triggerWords": "1girl, solo forcas, nude, depth of field, indoors,\n4+boys, Gangbang, Group Sex, Multiple Boys, Multiple Penises, black boys, no face boys, Men in black,\nhetero, sex, group sex, oral, fellatio, irrumatio, paizuri, \nspread legs, spitroast, sweat, gangbang, double penetration, triple penetration\n{open eyes | half-closed eyes | closed eyes | wide-eyed | ahegao, rolling eyes},\n{from side | from below | from above | from front},\n{upper body,| cowboy shot },\n{sex | mating press | amazon position | missionary | cowgirl position | sex from behind | doggystyle | prone bone sex | standing sex  | full nelson sex | arm held back, sex},\nclose up {pussy | ass | face | brests},\n",
    "order": 50
  },
  "434/WearingClothes_Anime_IL_V1.safetensors": {
    "triggerWords": "",
    "civitaiUrl": "yahoo",
    "order": 49
  },
  "434/Removing_Condom_IL_V2.safetensors": {
    "triggerWords": "",
    "civitaiUrl": "https://civitai.com/models/1987116",
    "order": 40
  },
  "character/geme/NIKKE/cinderella-nikke-richy-v1_ixl.safetensors": {
    "triggerWords": "",
    "civitaiUrl": "https://civitai.com/models/1019635"
  },
  "character/vtuber/hololive/blue journey (hololive).safetensors": {
    "triggerWords": "",
    "civitaiUrl": "https://civitai.com/models/1658118",
    "order": 0
  },
  "434/Bukkake_Adriana_IL_V1.safetensors": {
    "triggerWords": "",
    "civitaiUrl": "https://civitai.com/models/843783",
    "order": 3
  },
  "qinglong_detailedeye_z-imageV2%28comfy%29.safetensors": {
    "order": 0,
    "favorite": false
  },
  "434/Bala Asana_ill_v1.02.safetensors": {
    "order": 2
  },
  "434/1_HoldingSwimsuit_Anime_IL_V1.safetensors": {
    "order": 1,
    "triggerWords": "",
    "civitaiUrl": ""
  },
  "434/Dakimakura_Anime_IL_V1.safetensors": {
    "order": 4
  },
  "434/Deepthroat_PonytailHandle_Anime_IL_V1.safetensors": {
    "order": 5,
    "favorite": false
  },
  "434/Extreme_69_Anime_IL_V2.safetensors": {
    "order": 0
  },
  "434/FCHC2026_Dim64_IL_V1.safetensors": {
    "order": 6,
    "triggerWords": "",
    "civitaiUrl": ""
  },
  "434/FComic1To3Page_IL_V2.safetensors": {
    "order": 7,
    "triggerWords": "",
    "civitaiUrl": ""
  },
  "434/FComic_1to1000_IL_V2.safetensors": {
    "order": 8
  },
  "434/FComic_HardCore_IL_V2.safetensors": {
    "order": 9
  },
  "434/FComic_HardCore_Tentacle_Anime_IL_V01.safetensors": {
    "order": 10
  },
  "434/FComic_lastPage_IL_V2.safetensors": {
    "order": 11
  },
  "434/FC_HardCore_2025_IL_V1.safetensors": {
    "order": 12
  },
  "434/FFM_2Futa1Boy_SEX_Anime_IL_V1.safetensors": {
    "order": 13
  },
  "434/FFM_FutaFemboyPOVSEX_TAKESIDE_Anime_IL_V01.safetensors": {
    "order": 14
  },
  "434/Hentai_PI_IL_V1.safetensors": {
    "order": 15
  },
  "434/HPI2_Anime_IL_V1.safetensors": {
    "order": 16
  },
  "434/HugeBukkake_Anime_IL_V1.safetensors": {
    "order": 17
  },
  "434/HugeBukkake_Real_IL_V2.safetensors": {
    "order": 18
  },
  "434/IBW-977Z_Anime_IL_V2.safetensors": {
    "order": 19
  },
  "434/JAV_2TNOZ_Pony_V1.safetensors": {
    "order": 20
  },
  "434/JAV_BONY116_IL_V1.safetensors": {
    "order": 21
  },
  "434/JAV_Covers_SOUSAKAN_Real_IL_V01.safetensors": {
    "order": 22
  },
  "434/JAV_GTJ-135_BDSM_Anime_IL_V02.safetensors": {
    "order": 23
  },
  "434/JAV_GTJ130_IL_V1.safetensors": {
    "order": 24
  },
  "434/JAV_MIAA572_IL_V1.safetensors": {
    "order": 25
  },
  "434/JAV_MIZD-490_DeepThroatHandle_Anime_IL_V2.safetensors": {
    "order": 26
  },
  "434/JAV_MXGS-966_anime_IL_V2.safetensors": {
    "order": 27
  },
  "434/JAV_RopeBDSM_Cover_Anime_IL_V2.safetensors": {
    "order": 28
  },
  "434/JAV_RopeBDSM_Cover_Real_IL_V1.safetensors": {
    "order": 29
  },
  "434/JAV_START-400_Anime_V2.safetensors": {
    "order": 30
  },
  "434/Melting_Clothes_Slime_Anime_IL_V1.safetensors": {
    "order": 31
  },
  "434/MurakamiTeruaki_SSYsphere_Anime_IL_V2.safetensors": {
    "order": 32
  },
  "434/MurakamiTeruaki_Taimanin_Anime_IL_V2.safetensors": {
    "order": 33
  },
  "434/NikkeCC_IL_V1.safetensors": {
    "order": 34
  },
  "434/PaintCosplayEvent_Anime_IL_V1.safetensors": {
    "order": 35
  },
  "434/PublicSpacesFingering_Anime_IL_V1.safetensors": {
    "order": 36
  },
  "434/QB_Battle_PONY_V1.safetensors": {
    "order": 37
  },
  "434/QB_Defeat_IL_V1.safetensors": {
    "order": 38
  },
  "434/QuintupleInsert_Anime_IL_V2.safetensors": {
    "order": 39
  },
  "434/reversecowgirlposition.safetensors": {
    "order": 41
  },
  "434/Ripping_ Splitting_panties_Anime_V1.safetensors": {
    "order": 42
  },
  "434/SpreadPussy_STU_IL_V1.safetensors": {
    "order": 44
  },
  "434/SukebeExercise_Part2_Pony_V1.safetensors": {
    "order": 45
  },
  "434/TaimaninCC_IL_V2.safetensors": {
    "order": 46
  },
  "434/ToiletGirls_IL_V1.safetensors": {
    "order": 48
  },
  "character/anime/C-Control_Mashu_IlluXL.safetensors": {
    "order": 0
  },
  "character/anime/curezukyuun_Illust_v1.safetensors": {
    "order": 10
  },
  "character/anime/Kinomoto Illustrious.safetensors": {
    "order": 7
  },
  "character/anime/Kisaki Eri IL V2.safetensors": {
    "order": 1
  },
  "character/anime/mamitomoeILM.safetensors": {
    "order": 30
  },
  "character/anime/MilAiDou_1_8_Illustrious_Otome_New_V1_16dim_8alpha_3batch_CAME_Cosine_Res.safetensors": {
    "order": 2
  },
  "character/anime/Ooku_Jochu_FGO-000006.safetensors": {
    "order": 3
  },
  "character/anime/rebecca_v1.safetensors": {
    "order": 4
  },
  "character/anime/rikka-takarada-s1-illustriousxl-lora-nochekaiser.safetensors": {
    "order": 37
  },
  "character/anime/sailor_venus_animaginexl_v2.safetensors": {
    "order": 5
  },
  "cum/Cum_bubble_thick_cum_IL.safetensors": {
    "triggerWords": "",
    "civitaiUrl": "https://civitai.com/models/1591294"
  },
  "cum/cum_in_cleavage_illustrious.safetensors": {
    "triggerWords": "",
    "civitaiUrl": "https://civitai.com/models/1270261"
  },
  "cum/CumDrinkingBeforeAfter_v1.1.safetensors": {
    "triggerWords": "",
    "civitaiUrl": "https://civitai.com/models/1530307"
  },
  "cum/cumflood-NOOB-VPRED1.0-V1.0-loha-32-drop0.1-.safetensors": {
    "triggerWords": "",
    "civitaiUrl": "https://civitai.com/models/18665"
  },
  "character/vtuber/kojin/Akami_Karubi.safetensors": {
    "triggerWords": "",
    "civitaiUrl": "https://civitai.com/models/1590336"
  },
  "character/vtuber/hololive/４期生/amane_kanata_ilxl_v1.safetensors": {
    "triggerWords": "",
    "civitaiUrl": "https://civitai.com/models/17441"
  },
  "character/vtuber/hololive/２期生/aquaILXL.safetensors": {
    "triggerWords": "",
    "civitaiUrl": "https://civitai.com/models/1214295",
    "order": 0
  },
  "character/vtuber/hololive/０期生/tokinosoraextraoutfit-10(ILL).safetensors": {
    "order": 0
  },
  "character/vtuber/hololive/０期生/azki-04.safetensors": {
    "order": 2
  },
  "character/vtuber/hololive/０期生/CHAR-SakuraMikoPonyXL.safetensors": {
    "order": 3
  },
  "character/vtuber/hololive/０期生/checkpoint-e18_s774.safetensors": {
    "order": 5
  },
  "character/vtuber/hololive/０期生/hololive_roboco-san_noobAIXL11EPS-a2.safetensors": {
    "order": 1
  },
  "pose/Snoot_Challenge_Face_in_Hands__Twitter_Trend_Concept__IllustriousXL_and_NoobAI.safetensors": {
    "order": 43
  },
  "character/vtuber/hololive/０期生/miko_9th-09.safetensors": {
    "order": 4
  },
  "character/vtuber/hololive/harusaki_nodoka_XL.safetensors": {
    "order": 1
  },
  "character/vtuber/hololive/hololive idol uniform (color rise).safetensors": {
    "order": 2
  },
  "character/vtuber/hololive/hololivesummer2023swimsuitillustriousXL.safetensors": {
    "order": 3
  },
  "character/vtuber/hololive/Izuki_Michiru-AndroidXL.safetensors": {
    "order": 6
  },
  "character/vtuber/hololive/marineILXL.safetensors": {
    "order": 4
  },
  "character/vtuber/hololive/kroniIL-10.safetensors": {
    "order": 5
  },
  "character/vtuber/hololive/nodoka-09.safetensors": {
    "order": 7
  },
  "character/vtuber/hololive/２期生/ayamev2.safetensors": {
    "order": 1
  },
  "character/vtuber/hololive/２期生/yuzuki_choco_ilxl_v1.safetensors": {
    "order": 2
  },
  "character/vtuber/hololive/２期生/hololive summer 2023 swimsuit.safetensors": {
    "order": 3
  },
  "character/vtuber/hololive/２期生/murasakishion.safetensors": {
    "order": 4
  },
  "character/vtuber/hololive/２期生/oozora_subaru_ilxl_v1.safetensors": {
    "order": 5
  },
  "character/vtuber/hololive/３期生/marine_10outfits_illustrious.safetensors": {
    "order": 0
  },
  "character/vtuber/hololive/３期生/shiranui_flare_v10.safetensors": {
    "order": 1
  },
  "character/vtuber/hololive/３期生/shirogane_noel_v1.safetensors": {
    "order": 2
  },
  "character/vtuber/hololive/３期生/Uruha_Rushia.safetensors": {
    "order": 3
  },
  "character/vtuber/hololive/３期生/Usada_Pekora_V3.safetensors": {
    "order": 4
  },
  "character/vtuber/hololive/３期生/usadapekoraholonatsuparadiseIllustriousXL.safetensors": {
    "order": 5
  },
  "character/vtuber/hololive/３期生/usadapekorajiangshiIllustriousXL.safetensors": {
    "order": 6
  },
  "character/vtuber/hololive/３期生/Hoseki_Hololive_Pekomama_NoobAIXLEps11_v1.safetensors": {
    "order": 7
  },
  "character/vtuber/hololive/flow-glow/ChamKoganeiNikoIllustriousXL.safetensors": {
    "order": 0
  },
  "character/vtuber/hololive/flow-glow/Hololive_Su_Su-10.safetensors": {
    "order": 6
  },
  "character/vtuber/hololive/flow-glow/kikirara_vivi_IL.safetensors": {
    "order": 2
  },
  "character/vtuber/hololive/flow-glow/kikiraravivi11IllustriousXL.safetensors": {
    "order": 3
  },
  "character/vtuber/hololive/flow-glow/kikiraraviviholonatsuparadiseIllustriousXL.safetensors": {
    "order": 4
  },
  "character/vtuber/hololive/flow-glow/Kobo_Kanaeru_4th_Outfit__Hololive_Virtual_Youtuber__IllustriousXL_and_NoobAI.safetensors": {
    "order": 5
  },
  "character/vtuber/hololive/flow-glow/koganeinikoholonatsuparadiseIllustriousXL.safetensors": {
    "order": 1
  },
  "character/vtuber/hololive/flow-glow/mizumiyasu11IllustriousXL.safetensors": {
    "order": 7
  },
  "character/vtuber/hololive/flow-glow/mizumiyasuholonatsuparadiseIllustriousXL.safetensors": {
    "order": 8
  },
  "character/vtuber/hololive/flow-glow/mizumiyasuillustriousXL0.8.safetensors": {
    "order": 9
  },
  "character/vtuber/hololive/flow-glow/rindo_chihaya_ilxl_v1 (1).safetensors": {
    "order": 10
  },
  "character/vtuber/hololive/flow-glow/rindochihayaholonatsuparadiseIllustriousXL.safetensors": {
    "order": 11
  },
  "character/vtuber/hololive/flow-glow/rindochihayaillustriousXL0.8.safetensors": {
    "order": 12
  },
  "character/vtuber/hololive/flow-glow/rionaisaki.safetensors": {
    "order": 13
  },
  "character/vtuber/hololive/flow-glow/isakirionaholonatsuparadiseIllustriousXL.safetensors": {
    "order": 14
  },
  "character/vtuber/hololive/regloss/Hololive_Hajimejime-10.safetensors": {
    "order": 0
  },
  "character/vtuber/hololive/regloss/Hololive_Kanadenade-10.safetensors": {
    "order": 1
  },
  "character/vtuber/hololive/regloss/Hololive_Ririkarika-10.safetensors": {
    "order": 2
  },
  "character/vtuber/hololive/regloss/ichijouririkaholonatsuparadiseIllustriousXL.safetensors": {
    "order": 3
  },
  "character/vtuber/hololive/regloss/raden.safetensors": {
    "order": 4
  },
  "character/vtuber/hololive/regloss/ChamJuufuuteiRadenNoob.safetensors": {
    "order": 5
  },
  "NTR/Doggy_style_sex_on_a_balcony_viewed_from_behind.safetensors": {
    "triggerWords": "",
    "civitaiUrl": ""
  },
  "tool/sound_effects.safetensors": {
    "favoriteLists": [
      "お気に入り"
    ]
  },
  "situation/Drunk_and_horny.safetensors": {
    "triggerWords": "",
    "civitaiUrl": "",
    "customTags": [
      "<lora:Drunk_and_horny:0.5>Drunk_and_horny, 1girl,hetero,1boy, nude,sex,lying, holding, drinking, beer can, drunk, beer can, sex from behind,Drunk and horny,",
      "<lora:Drunk_and_horny:0.5>Drunk_and_horny, 1girl,mixed bathing,1boy, grabbing from behind, water, nude,hetero,bathroom, kiss, nipples, sitting, french kiss, bathtub,cowboy shot, steaming body, holding beer can,wet, beer can,Drunk and horny,tongue out, full-face blush, drunk,",
      "<lora:Drunk_and_horny:0.5>Drunk_and_horny, 1girl,1boy,hetero, nude,nipples,lying,oral,ass,pussy,wet, on back,navel,cunnilingus, beer can, holding,drinking, Drunk and horny,drunk, blush, pussy juice, spread legs,",
      "<lora:Drunk_and_horny:0.5>Drunk_and_horny, 1girl,breasts,nipples,hetero,sex,1boy, beer can, holding, straddling,nude,cowgirl position,Drunk and horny,drunk, vaginal, penis, grabbing waist, uncensored, cum in pussy,",
      "<lora:Drunk_and_horny:0.5>Drunk_and_horny, 1girl,hetero,1boy,penis,nipples, pov hands, paizuri,breasts,Drunk and horny, uncensored, holding,beer can,projectile cum, facial, hand up. breasts squeezed together, drunk,blush, grabbing another's breast,",
      "<lora:Drunk_and_horny:0.5>Drunk_and_horny, 1girl,hetero,penis,1boy,fellatio, hand up,steaming body, oral,nude,beer can,drunk and horny, cumdrip, uncensored, (holding beer can:1.2),blush, drunk,all fours, cum on tongue, open mouth,",
      "<lora:Drunk_and_horny:0.5>Drunk_and_horny, 1girl,hetero,penis,1boy,fingering,breast sucking, cum in anal, uncensored,blush, drunk,moaning, solo focus, solo, wet, sweat, sweatdrop, drunk and horny,drunk,anal sex,penis, one eye closed, enjoy,spread legs, full body, sitting on lap, arm around shoulders,"
    ]
  },
  "gangbang/rin_fera.safetensors": {
    "customTags": [
      "<lora:rin_fera:0.9>rin_feraV1,  1girl,multiple boys,sweatdrop,  penis,multiple penises, steaming body,  hetero,breasts, cumdrip, half-closed eyes,  group sex,handjob, seductive smile,",
      "<lora:rin_fera:0.9>rin_feraV1,  1girl,multiple boys,half-closed eyes, bukkake, cum on nose,  handjob,hetero,projectile cum, steaming body, cum on hair,  penis,group sex,oral,cum overflow, open mouth, cum on body,  multiple penises,fellatio, tongue, licking,",
      "<lora:rin_fera:0.9>rin_feraV1,  1girl,cum,lying,on back,  multiple boys,penis,tongue,  breasts,multiple penises,  hetero,nipples,group sex,oral,  double handjob,fellatio,",
      "<lora:rin_fera:0.9>rin_feraV1,  1girl,cum,lying,on back,  multiple boys,penis,tongue,  breasts,multiple penises,  hetero,nipples,group sex,oral,  double handjob,fellatio,paizuri, pov hands,  grabbing another's breast,",
      "<lora:rin_fera:0.9>rin_feraV1,  1girl,cum,lying,on back,half-closed eyes,  multiple boys,penis,tongue, bukkake,  breasts,multiple penises,emjoy,cum on body,  hetero,nipples,group sex,oral,grabbing,  double handjob,fellatio,sex,legs up,",
      "<lora:rin_fera:0.9>rin_feraV1,  penis,oral,fellatio,cumdrip, projectile cum,  multiple boys,hetero,cum overflow, bukkake, open mouth,  1girl,handjob,group sex,multiple penises,cum on face,licking,  breasts,double handjob,blindfold,cum on body, cum on clothes,"
    ],
    "tagImages": {
      "<lora:rin_fera:0.9>rin_feraV1,  1girl,multiple boys,sweatdrop,  penis,multiple penises, steaming body,  hetero,breasts, cumdrip, half-closed eyes,  group sex,handjob, seductive smile,": "gangbang/.tag_images/rin_fera_75eec4c681bb.jpg",
      "<lora:rin_fera:0.9>rin_feraV1,  1girl,multiple boys,half-closed eyes, bukkake, cum on nose,  handjob,hetero,projectile cum, steaming body, cum on hair,  penis,group sex,oral,cum overflow, open mouth, cum on body,  multiple penises,fellatio, tongue, licking,": "gangbang/.tag_images/rin_fera_3f02a20ebe8e.jpg",
      "<lora:rin_fera:0.9>rin_feraV1,  1girl,cum,lying,on back,  multiple boys,penis,tongue,  breasts,multiple penises,  hetero,nipples,group sex,oral,  double handjob,fellatio,": "gangbang/.tag_images/rin_fera_58ac59bd793c.jpg",
      "<lora:rin_fera:0.9>rin_feraV1,  1girl,cum,lying,on back,  multiple boys,penis,tongue,  breasts,multiple penises,  hetero,nipples,group sex,oral,  double handjob,fellatio,paizuri, pov hands,  grabbing another's breast,": "gangbang/.tag_images/rin_fera_79f8c45a1515.jpg",
      "<lora:rin_fera:0.9>rin_feraV1,  1girl,cum,lying,on back,half-closed eyes,  multiple boys,penis,tongue, bukkake,  breasts,multiple penises,emjoy,cum on body,  hetero,nipples,group sex,oral,grabbing,  double handjob,fellatio,sex,legs up,": "gangbang/.tag_images/rin_fera_4ca7549db010.jpg",
      "<lora:rin_fera:0.9>rin_feraV1,  penis,oral,fellatio,cumdrip, projectile cum,  multiple boys,hetero,cum overflow, bukkake, open mouth,  1girl,handjob,group sex,multiple penises,cum on face,licking,  breasts,double handjob,blindfold,cum on body, cum on clothes,": "gangbang/.tag_images/rin_fera_befe3144e4af.jpg"
    }
  },
  "character/anime/bulmaill-000004.safetensors": {
    "favoriteLists": [],
    "order": 60
  },
  "character/anime/checkpoint-e39_s819 (1).safetensors": {
    "triggerWords": "bulla, 1girl, solo, blue eyes, long hair, blue hair, bangs,hairband, hoop earrings, red crop top, choker, elbow gloves, fingerless gloves, midriff, navel, belt, red skirt, thighhighs,",
    "civitaiUrl": "",
    "order": 61
  },
  "character/geme/DQ/dqh2_meena_v01.safetensors": {
    "triggerWords": "",
    "civitaiUrl": "",
    "order": 15
  },
  "character/geme/その他/Amazon.safetensors": {
    "customTags": [
      "4m4z0n, blonde hair, green eyes, long hair, leg tattoo, hair ornament, large breasts, thick thighs, circlet, feather hair ornament,gloves, bikini armor, black gloves, navel, armlet, black footwear,"
    ]
  },
  "character/vtuber/aogiri/chiyoura_chiyomi_千代浦蝶美あおぎり高校通常衣装_LoRA-000002.safetensors": {
    "order": 3
  },
  "character/vtuber/aogiri/gabu_rieru_ilxl_v1.safetensors": {
    "order": 4
  },
  "character/vtuber/aogiri/ishikari_akari_石狩あかりあおぎり高校初期衣装_LoRA.safetensors": {
    "order": 5
  },
  "character/vtuber/aogiri/Minazuki_Natsuki_IL_1.0.safetensors": {
    "order": 6
  },
  "character/vtuber/aogiri/kurikoma_komaru_ilxl_v1.safetensors": {
    "order": 0
  },
  "character/vtuber/aogiri/ooshiro_mashiro_ilxl_v1.safetensors": {
    "order": 2
  },
  "character/vtuber/aogiri/otodama_tamako_ilxl_v1.safetensors": {
    "order": 1
  },
  "character/vtuber/aogiri/puwapuwa_popura-10.safetensors": {
    "order": 7
  },
  "character/vtuber/aogiri/yamaguro_nekuro_ilxl_v1.safetensors": {
    "order": 8
  },
  "character/vtuber/aogiri/春雨麗女IL.safetensors": {
    "order": 9
  },
  "LoRA/character/geme/DQ/dqbianca-illu-nvwls-v1.safetensors": {
    "favoriteLists": [
      "Misc",
      "お気に入り"
    ]
  },
  "LoRA/sex/hundjob/Condom_on_mouth.safetensors": {
    "triggerWords": "",
    "civitaiUrl": "",
    "customTags": [
      "<lora:Condom_on_mouth:0.7>  Condom on mouth, solo,  simple background,white background , closed mouth, lips,  looking at viewer,",
      "POV,  <lora:Condom_on_mouth:0.8>  1girl,Condom on mouth,  hetero,penis,  oral,1boy,  fellatio,  green Condom on penis,  testicles,  half-closed eyes, looking to the side, pov,  uncensored,  putting on a condom with the mouth,  hand-and-mouth condom application,  she precisely fits the condom in place With only two fingers,",
      "<lora:Condom_on_mouth:0.7>Condom_on_mouth,adjusting Condom,  penis,  hetero,from side,  (A green condom is on the penis),  1girl,1boy,  uncensored,  oral, sweatdrop, heavy breathing,  veins,  putting on a condom with the mouth,  hand-and-mouth condom application,blush, closed eyes,  she precisely fits the condom in place With only two fingers,"
    ],
    "tagImages": {
      "<lora:Condom_on_mouth:0.7>  Condom on mouth, solo,  simple background,white background , closed mouth, lips,  looking at viewer,": "LoRA/sex/hundjob/.tag_images/Condom_on_mouth_cc479e9a0acf.jpg",
      "POV,  <lora:Condom_on_mouth:0.8>  1girl,Condom on mouth,  hetero,penis,  oral,1boy,  fellatio,  green Condom on penis,  testicles,  half-closed eyes, looking to the side, pov,  uncensored,  putting on a condom with the mouth,  hand-and-mouth condom application,  she precisely fits the condom in place With only two fingers,": "LoRA/sex/hundjob/.tag_images/Condom_on_mouth_9223f8f65b24.jpg",
      "<lora:Condom_on_mouth:0.7>Condom_on_mouth,adjusting Condom,  penis,  hetero,from side,  (A green condom is on the penis),  1girl,1boy,  uncensored,  oral, sweatdrop, heavy breathing,  veins,  putting on a condom with the mouth,  hand-and-mouth condom application,blush, closed eyes,  she precisely fits the condom in place With only two fingers,": "LoRA/sex/hundjob/.tag_images/Condom_on_mouth_3124291641a7.jpg"
    }
  },
  "LoRA/434/XXX_GangBang_IL_V1.safetensors": {
    "favoriteLists": [
      "Misc"
    ]
  },
  "LoRA/tool/sound_effects.safetensors": {
    "favoriteLists": [
      "Misc",
      "お気に入り"
    ]
  },
  "character/persona/dqpom-illu-nvwls-v1.safetensors": {
    "order": 0
  },
  "character/persona/p3aigis-ill.safetensors": {
    "order": 1
  },
  "character/persona/Lavenza_ILLUS_c.safetensors": {
    "order": 2
  },
  "character/persona/p3chidori-ill.safetensors": {
    "order": 3
  },
  "character/persona/p3chihiro-ill.safetensors": {
    "order": 4
  },
  "character/persona/p3elizabeth-ill.safetensors": {
    "order": 5
  },
  "character/persona/p3fuuka-illV2.safetensors": {
    "order": 6
  },
  "character/persona/p3kotone-ill.safetensors": {
    "order": 7
  },
  "character/persona/p3mitsuru-illV2.safetensors": {
    "order": 8
  },
  "character/persona/p3natsuki-ill.safetensors": {
    "order": 9
  },
  "character/persona/p3toriumi-ill.safetensors": {
    "order": 10
  },
  "character/persona/p3yukari-ill.safetensors": {
    "order": 11
  },
  "character/persona/p3yuko-ill.safetensors": {
    "order": 12
  },
  "character/persona/p4aika-ill.safetensors": {
    "order": 13
  },
  "character/persona/p4ayane-ill.safetensors": {
    "order": 14
  },
  "character/persona/p4chie-ill-V2.safetensors": {
    "order": 15
  },
  "character/persona/p4ebihara-ill.safetensors": {
    "order": 16
  },
  "character/persona/p4kashiwagi-ill.safetensors": {
    "order": 17
  },
  "character/persona/p4margaret-ill.safetensors": {
    "order": 18
  },
  "character/persona/p4marie-ill.safetensors": {
    "order": 19
  },
  "character/persona/p4naoto-illV2.safetensors": {
    "order": 20
  },
  "character/persona/p4rise-illV3.safetensors": {
    "order": 21
  },
  "character/persona/p4yukiko-ill-V2.safetensors": {
    "order": 22
  },
  "character/persona/p4yukiko-ill-V3.safetensors": {
    "order": 23
  },
  "character/persona/p4yumi-ill.safetensors": {
    "order": 24
  },
  "character/persona/p5annV4-ill.safetensors": {
    "order": 25
  },
  "character/persona/p5chihaya-ill.safetensors": {
    "order": 26
  },
  "character/persona/p5futaba-ill.safetensors": {
    "order": 27
  },
  "character/persona/p5haru-illV2.safetensors": {
    "order": 28
  },
  "character/persona/p5hifumi-illV2.safetensors": {
    "order": 29
  },
  "character/persona/p5kawakami-ill.safetensors": {
    "order": 30
  },
  "character/persona/p5makoto-illV3-cool.safetensors": {
    "order": 31
  },
  "character/persona/p5ohya-ill.safetensors": {
    "order": 32
  },
  "character/persona/p5sae-ill.safetensors": {
    "order": 33
  },
  "character/persona/p5shiho-ill.safetensors": {
    "order": 34
  },
  "character/persona/p5tae-ill.safetensors": {
    "order": 35
  },
  "character/persona/p5yoshizawa-ill.safetensors": {
    "order": 36
  },
  "character/persona/p5yoshizawa-illV2.safetensors": {
    "order": 37
  },
  "character/geme/DQ/anlucia_dqx.safetensors": {
    "order": 23
  },
  "character/geme/DQ/Barbara.safetensors": {
    "order": 21
  },
  "character/geme/DQ/Daisy.safetensors": {
    "order": 44
  },
  "character/geme/DQ/dq3fighter-pdxl-nvwls-v1.safetensors": {
    "order": 6
  },
  "character/geme/DQ/dq4_sofia_v01.safetensors": {
    "order": 12
  },
  "character/geme/DQ/dqbianca-illu-nvwls-v1.safetensors": {
    "order": 17
  },
  "character/geme/DQ/dqdebora-illu-nvwls-v1 (1).safetensors": {
    "order": 18
  },
  "character/geme/DQ/dqflora-illu-nvwls-v1.safetensors": {
    "order": 19
  },
  "character/geme/DQ/dqh2_alena_v01.safetensors": {
    "order": 13
  },
  "character/geme/DQ/dqh2_aurora_v02.safetensors": {
    "order": 30
  },
  "character/geme/DQ/dqh2_maya_v01.safetensors": {
    "order": 14
  },
  "character/geme/DQ/dqlaura-illu-nvwls-v1.safetensors": {
    "order": 0
  },
  "character/geme/DQ/dqmaribel-illu-nvwls-v1.safetensors": {
    "order": 24
  },
  "character/geme/DQ/dqpom-illu-nvwls-v1.safetensors": {
    "order": 1
  },
  "character/geme/DQ/dqsoldier-illu-nvwls-v1 (1).safetensors": {
    "order": 11
  },
  "character/geme/DQ/Female_Builder.safetensors": {
    "order": 43
  },
  "character/geme/DQ/fosse dq7 2outfits_illustriousXL.safetensors": {
    "order": 25
  },
  "character/geme/DQ/Fosse.safetensors": {
    "order": 26
  },
  "character/geme/DQ/GemmaDQ-illu-bsinky-v1.safetensors": {
    "order": 27
  },
  "character/geme/DQ/Heroine_Roto.safetensors": {
    "order": 3
  },
  "character/geme/DQ/Heros_daughter.safetensors": {
    "order": 20
  },
  "character/geme/DQ/Hoseki_DragonQuest_Jade_IllustriousXL_v1.safetensors": {
    "order": 36
  },
  "character/geme/DQ/Jessica_Albert_(Character)_ILXL.safetensors": {
    "order": 28
  },
  "character/geme/DQ/Jessica-DQ8-Illustrious.safetensors": {
    "order": 29
  },
  "character/geme/DQ/Jester.safetensors": {
    "order": 4
  },
  "character/geme/DQ/Warrior_-_Dragon_Quest_Illustrious.safetensors": {
    "order": 10
  },
  "character/geme/DQ/kp_PrincessOfSamantoriaDragonQuestIllustrious_v1_0.safetensors": {
    "order": 2
  },
  "character/geme/DQ/Maiyu.safetensors": {
    "order": 31
  },
  "character/geme/DQ/Maya_DQXI.safetensors": {
    "order": 37
  },
  "character/geme/DQ/Maya.safetensors": {
    "order": 38
  },
  "character/geme/DQ/maya02.safetensors": {
    "order": 16
  },
  "character/geme/DQ/Merchant_(Character)_ILXL.safetensors": {
    "order": 5
  },
  "character/geme/DQ/Mireyu.safetensors": {
    "order": 22
  },
  "character/geme/DQ/Ogre.safetensors": {
    "order": 32
  },
  "character/geme/DQ/Priest_(Character)_ILXL.safetensors": {
    "order": 7
  },
  "character/geme/DQ/Princess_Leona.safetensors": {
    "order": 33
  },
  "character/geme/DQ/Rikka.safetensors": {
    "order": 34
  },
  "character/geme/DQ/Sage_-_Dragon_Quest_Illustrious.safetensors": {
    "order": 8
  },
  "character/geme/DQ/Serena_-_Dragon_Quest.safetensors": {
    "order": 40
  },
  "character/geme/DQ/serena02.safetensors": {
    "order": 39
  },
  "character/geme/DQ/Tania.safetensors": {
    "order": 35
  },
  "character/geme/DQ/Thief.safetensors": {
    "order": 9,
    "favoriteLists": []
  },
  "character/geme/DQ/veronica dq11_illustriousXL.safetensors": {
    "order": 41
  },
  "character/geme/DQ/Veronica-IL.safetensors": {
    "order": 42
  },
  "character/geme/FF/RikkuFFXIllustriou.safetensors": {
    "order": 39
  },
  "character/geme/DQ/RikkuFFXIllustriou.safetensors": {
    "order": 37
  },
  "character/anime/gundam/kp_DeuxMurasameGundamGQIllustrious_v1_1.safetensors": {
    "order": 8
  },
  "character/anime/gundam/Shiiko_Sugai.safetensors": {
    "order": 16
  },
  "character/anime/gundam/gundam_gquuuuuux_shiiko_sugai.safetensors": {
    "order": 0
  },
  "character/anime/gundam/deuxmurasameillv3.1.safetensors": {
    "order": 1
  },
  "character/anime/gundam/GQuX-amate_yuzuriha_XL(ill)v10.safetensors": {
    "order": 2
  },
  "character/anime/gundam/Lalah_Sune_-_100percent_-_manga02.safetensors": {
    "order": 9
  },
  "character/anime/gundam/deux_murasame_il.safetensors": {
    "triggerWords": "",
    "civitaiUrl": "https://civitai.com/models/1657884",
    "order": 3
  },
  "character/anime/A-Bao A Qu, the Lightless Shadow illusXL v2.1.safetensors": {
    "order": 9
  },
  "character/anime/Anzu_Mazaki_YGO_Duel_Monsters-000006.safetensors": {
    "order": 42
  },
  "character/anime/Apprentice Illusion Magician illuXL v1.safetensors": {
    "order": 43
  },
  "character/anime/arcanashadow_Illust_v1.safetensors": {
    "order": 11
  },
  "character/anime/Asuka_Tenjoin_Noob_Lora.safetensors": {
    "order": 44
  },
  "character/anime/Bulma__ブルマ_-_Dragon_Ball_Classic.safetensors": {
    "order": 59
  },
  "character/anime/corrector yui-ill-01.safetensors": {
    "order": 6
  },
  "character/anime/cure_eclair05.safetensors": {
    "order": 12
  },
  "character/anime/cureanswer.safetensors": {
    "order": 13
  },
  "character/anime/curearcanashadow05.safetensors": {
    "order": 14
  },
  "character/anime/cureidol_v2_IL.safetensors": {
    "order": 15
  },
  "character/anime/curewink_v2_IL.safetensors": {
    "order": 17
  },
  "character/anime/dark_magician_girl_illust_scarxzys.safetensors": {
    "order": 45
  },
  "character/anime/Dragonmaid latys illuXL v2.safetensors": {
    "order": 46
  },
  "character/anime/fujiwara_chika_v2.safetensors": {
    "order": 18
  },
  "character/anime/haruhi-suzumiya-s1-illustriousxl-lora-nochekaiser.safetensors": {
    "order": 19
  },
  "character/anime/HighschoolOfTheDead_MiyamotoRei_IlluXL.safetensors": {
    "order": 24
  },
  "character/anime/HighschoolOfTheDead_TakagiSaya_IlluXL.safetensors": {
    "order": 25
  },
  "character/anime/ichika_nakano-gotoubun_no_hanayome_s2-ixl-anime-soralz.safetensors": {
    "order": 38
  },
  "character/anime/itsuki_nakano-gotoubun_no_hanayome_s2-ixl-anime-soralz.safetensors": {
    "order": 39
  },
  "character/anime/JN_Saeko_Busujima_Illus.safetensors": {
    "order": 26
  },
  "character/anime/JN_Shizuka_Marikawa_Illus.safetensors": {
    "order": 27
  },
  "character/anime/kamishiro_rio_ilxl_v1.safetensors": {
    "order": 47
  },
  "character/anime/Lovely labrynth of the silver castle illuXL v2.safetensors": {
    "order": 48
  },
  "character/anime/Magi Magi Magician Gal illuXL v1.1.safetensors": {
    "order": 49
  },
  "character/anime/Mai_Valentine_Noob_Lora.safetensors": {
    "order": 50
  },
  "character/anime/MALICE Pawn March Hare illusXL v2.safetensors": {
    "order": 55
  },
  "character/anime/MALICE Pawn White Rabbit illuXL v1.safetensors": {
    "order": 51
  },
  "character/anime/MALICE Queen White Binder illuXL v1.2.safetensors": {
    "order": 56
  },
  "character/anime/Maou_ILXL.safetensors": {
    "order": 29
  },
  "character/anime/mgrcminamirena_IL.safetensors": {
    "order": 57
  },
  "character/anime/miku_nakano-gotoubun_no_hanayome_s2-ixl-anime-soralz (1).safetensors": {
    "order": 40
  },
  "character/anime/mikuru-asahina-s1-illustriousxl-lora-nochekaiser.safetensors": {
    "order": 20
  },
  "character/anime/nijigaoka_mashiro_illust_scarxzys.safetensors": {
    "order": 16
  },
  "character/anime/nino_nakano-gotoubun_no_hanayome_s2-ixl-anime-soralz.safetensors": {
    "order": 41
  },
  "character/anime/Nurse dragonmaid illuXL v1.1.safetensors": {
    "order": 52
  },
  "character/anime/ruruka05.safetensors": {
    "order": 8,
    "alias": ""
  },
  "character/anime/saotome_rei_ilxl_v1.safetensors": {
    "order": 53
  },
  "character/anime/akemihomuraILM.safetensors": {
    "order": 31
  },
  "character/anime/kanamemadokaILM.safetensors": {
    "order": 32
  },
  "character/anime/sayaka-miki-s1-illustriousxl-lora-nochekaiser.safetensors": {
    "order": 34
  },
  "character/anime/SSSSGridman_ShinjouAkane_IlluXL.safetensors": {
    "order": 35
  },
  "character/anime/SSSSGridman_TakaradaRikka_IlluXL.safetensors": {
    "order": 36
  },
  "character/anime/Tamaki_Iroha.safetensors": {
    "order": 33
  },
  "character/anime/Tearlaments rulkallos illusXL v3.safetensors": {
    "order": 54
  },
  "character/anime/Witchcrafter Madame Verre illuXL v1.safetensors": {
    "order": 58
  },
  "character/anime/yuki-nagato-s1-illustriousxl-lora-nochekaiser.safetensors": {
    "order": 21
  },
  "character/anime/yusa_emi_XL_illustrious-noob_v1.safetensors": {
    "order": 22
  },
  "character/anime/YusaEmiV12IllustriousXL.safetensors": {
    "order": 23
  },
  "character/anime/ZangyaDragonballIXL.safetensors": {
    "order": 62
  },
  "character/geme/DQ/dqmaam-illu-nvwls-v1.safetensors": {
    "order": 18
  },
  "character/anime/gundam/Vani_Kanchana_-_Gundam_GquuuuuuX_ILXL.safetensors": {
    "order": 8
  },
  "character/geme/DQ/Maam_(Character)_ILXL.safetensors": {
    "order": 28
  },
  "character/anime/old/Morisawa_Yuu_-_Magical_Angel_Creamy_Mami.safetensors": {
    "triggerWords": "",
    "customTags": [
      "yuu morisawa,1girl,brown eyes,blue hair,short hair,bangs,hood,short sleeves,"
    ]
  }
}